CHANGES.txt
COPYING
MANIFEST.in
README.txt
setup.py
unity_avindicator/__init__.py
unity_avindicator/avindicator.py
unity_avindicator/webmic.py
unity_avindicator.egg-info/PKG-INFO
unity_avindicator.egg-info/SOURCES.txt
unity_avindicator.egg-info/dependency_links.txt
unity_avindicator.egg-info/entry_points.txt
unity_avindicator.egg-info/not-zip-safe
unity_avindicator.egg-info/requires.txt
unity_avindicator.egg-info/top_level.txt
unity_avindicator/icons/eye.png
unity_avindicator/icons/eye_green.png
unity_avindicator/icons/eye_red.png
unity_avindicator/icons/mic.png
unity_avindicator/icons/mic_green.png
unity_avindicator/icons/mic_red.png