Metadata-Version: 1.1
Name: unity-avindicator
Version: 0.7
Summary: AV enable/disable Unity Application Indicator
Home-page: http://www.github.com/mgmtech/sys76_unity_webmic
Author: Matthew Miller
Author-email: matthewgarrettmiller@gmail.com
License: COPYING
Keywords: gazelle system76 avcontrol webcam microphone appindicator indicator
Platform: UNKNOWN
Classifier: Development Status :: 3 - Alpha
Classifier: License :: OSI Approved :: GNU General Public License v3 (GPLv3)
Classifier: Programming Language :: Python :: 2.7
Classifier: Topic :: Multimedia :: Sound/Audio
